gptdb_tugraph_plugins/__init__.py
gptdb_tugraph_plugins/_version.py
gptdb_tugraph_plugins/libs/leiden-0.1.0-linux-x86_64.so
gptdb_tugraph_plugins-0.1.0.dist-info/METADATA
gptdb_tugraph_plugins-0.1.0.dist-info/WHEEL
gptdb_tugraph_plugins-0.1.0.dist-info/top_level.txt
gptdb_tugraph_plugins-0.1.0.dist-info/RECORD
