Metadata-Version: 2.1
Name: gptdb-tugraph-plugins
Version: 0.1.0
Summary: TuGraph plugins python package used in GPT-DB.
Home-page: https://github.com/khulnasoft-lab/gptdb-tugraph-plugins
Author: 
Author-email: 
Keywords: TuGraph GPT-DB graph LLM
Classifier: Programming Language :: Python :: 3.8
Classifier: Programming Language :: Python :: 3.9
Classifier: Programming Language :: Python :: 3.10
Classifier: Programming Language :: Python :: 3.11
Requires-Python: >=3.8
